MANIFEST.in
README.md
setup.py
paymentsos/__init__.py
paymentsos/authorizations.py
paymentsos/captures.py
paymentsos/charges.py
paymentsos/client.py
paymentsos/credits.py
paymentsos/customers.py
paymentsos/enumerators.py
paymentsos/exceptions.py
paymentsos/payment_methods.py
paymentsos/payments.py
paymentsos/redirections.py
paymentsos/refunds.py
paymentsos/tokens.py
paymentsos/utils.py
paymentsos/voids.py
paymentsos_python.egg-info/PKG-INFO
paymentsos_python.egg-info/SOURCES.txt
paymentsos_python.egg-info/dependency_links.txt
paymentsos_python.egg-info/not-zip-safe
paymentsos_python.egg-info/requires.txt
paymentsos_python.egg-info/top_level.txt