Metadata-Version: 1.0
Name: paymentsos-python
Version: 0.1.0
Summary: API wrapper for PaymentsOS written in Python
Home-page: https://github.com/GearPlug/paymentsos-python
Author: Miguel Ferrer
Author-email: ingferrermiguel@gmail.com
License: MIT
Platform: UNKNOWN
